domhmm/.DS_Store
domhmm/__init__.py
domhmm/_version.py
domhmm/analysis/__init__.py
domhmm/analysis/base.py
domhmm/analysis/domhmm.py
domhmm/tests/.DS_Store
domhmm/tests/__init__.py
domhmm/tests/test_base.py
domhmm/tests/test_domhmm.py
domhmm/tests/data/.md_center_mol_last2mus.xtc_offsets.lock
domhmm/tests/data/.md_center_mol_last2mus.xtc_offsets.npz
domhmm/tests/data/first_lower_apl.pickle
domhmm/tests/data/first_lower_pbc_idx.pickle
domhmm/tests/data/first_lower_vor.pickle
domhmm/tests/data/first_lower_weight.pickle
domhmm/tests/data/first_order_parameters.pickle
domhmm/tests/data/first_upper_apl.pickle
domhmm/tests/data/first_upper_pbc_idx.pickle
domhmm/tests/data/first_upper_vor.pickle
domhmm/tests/data/first_upper_weight.pickle
domhmm/tests/data/md_center_mol_last2mus.xtc
domhmm/tests/data/mem.tpr
domhmm/tests/data/symmetric_hmm.pickle
domhmm-1.1.1.dist-info/licenses/AUTHORS.md
domhmm-1.1.1.dist-info/licenses/LICENSE
domhmm-1.1.1.dist-info/METADATA
domhmm-1.1.1.dist-info/WHEEL
domhmm-1.1.1.dist-info/top_level.txt
domhmm-1.1.1.dist-info/RECORD
