Metadata-Version: 2.4
Name: domhmm
Version: 1.1.1
Summary: HMM model to determine Lo or Ld domains from coarse grained or atomistic MD simulations.
Author: Marius FW Trollmann, Yusuf Eren Tunç
Author-email: Marius FW Trollmann <marius.trollmann@fau.de>, Yusuf Eren Tunç <eren.tunc@fau.de>
Maintainer-email: Marius FW Trollmann <marius.trollmann@fau.de>, Yusuf Eren Tunç <eren.tunc@fau.de>
License:                     GNU GENERAL PUBLIC LICENSE
Keywords: molecular simulations
Requires-Python: >=3.9
License-File: LICENSE
License-File: AUTHORS.md
Requires-Dist: MDAnalysis>=2.0.0
Requires-Dist: hmmlearn==0.3.2
Requires-Dist: networkx>=3.0.0
Requires-Dist: numpy<2.0.0,>=1.26.0
Requires-Dist: scikit-learn>=1.4.0
Requires-Dist: scipy>=1.13.0
Provides-Extra: test
Requires-Dist: pytest>=6.0; extra == "test"
Requires-Dist: pytest-xdist>=2.5; extra == "test"
Requires-Dist: pytest-cov>=3.0; extra == "test"
Provides-Extra: doc
Requires-Dist: sphinx; extra == "doc"
Requires-Dist: sphinx_rtd_theme; extra == "doc"
Dynamic: author
Dynamic: license-file
Dynamic: requires-python
